Metadata-Version: 2.4
Name: dagster-cloud-examples
Version: 1.12.13
Author-email: Elementl <hello@elementl.com>
License: Apache-2.0
Classifier: Programming Language :: Python :: 3.12
Classifier: License :: OSI Approved :: Apache Software License
Classifier: Operating System :: OS Independent
Requires-Python: <3.13,>=3.9
Requires-Dist: dagster-cloud==1.12.13
Provides-Extra: tests
Requires-Dist: mypy; extra == "tests"
Requires-Dist: pylint; extra == "tests"
Requires-Dist: pytest; extra == "tests"
